pySpack/__init__.py
pySpack/pyspack.py
pySpack/test_pyspack.py
pySpack/core/__init__.py
pySpack/core/exec_cmd.py
pySpack-0.2.1.dist-info/METADATA
pySpack-0.2.1.dist-info/WHEEL
pySpack-0.2.1.dist-info/top_level.txt
pySpack-0.2.1.dist-info/RECORD
