Metadata-Version: 2.1
Name: pySpack
Version: 0.2.1
Summary: Python wrapper for few Spack's commands
Home-page: https://github.com/NexSabre/pySpack
Author: Nex Sabre
Author-email: nexsabre@protonmail.com
License: UNKNOWN
Platform: UNKNOWN
Classifier: Programming Language :: Python :: 3.5
Classifier: Programming Language :: Python :: 3.6
Classifier: Programming Language :: Python :: 3.7
Classifier: Programming Language :: Python :: 3.8
Classifier: License :: OSI Approved :: MIT License
Requires-Python: >=3.5
